.coveragerc
MANIFEST.in
README.md
requirements.txt
setup.cfg
setup.py
tox.ini
suite_dog.egg-info/PKG-INFO
suite_dog.egg-info/SOURCES.txt
suite_dog.egg-info/dependency_links.txt
suite_dog.egg-info/not-zip-safe
suite_dog.egg-info/top_level.txt
suitedog/__init__.py
suitedog/metrics/__init__.py
suitedog/metrics/db_time_parser.py
suitedog/metrics/settings.py
suitedog/metrics/status_code_parser.py