Metadata-Version: 1.1
Name: suite-dog
Version: 0.2.0
Summary: Datadog metrices
Home-page: https://github.com/suitepad-gmbh/datadog
Author: Rajat Gupta
Author-email: rajat.gupta@suitepad.de
License: UNKNOWN
Platform: UNKNOWN
Classifier: Environment :: Plugins
Classifier: Intended Audience :: Developers
Classifier: Natural Language :: English
Classifier: Operating System :: OS Independent
Classifier: Programming Language :: Python
Classifier: Topic :: Office/Business
